[{"type":"U","date":"2018-04-18T01:20:00.000Z","volume":10000,"label":"U","price":0.034},{"type":"A","date":"2018-04-18T01:38:34.000Z","volume":50000,"label":" ","price":0.036},{"type":"A","date":"2018-04-18T01:44:50.000Z","volume":50000,"label":" ","price":0.037},{"type":"B","date":"2018-04-18T01:45:35.000Z","volume":950000,"label":" ","price":0.037},{"type":"B","date":"2018-04-18T01:48:12.000Z","volume":10000,"label":" ","price":0.037},{"type":"A","date":"2018-04-18T03:18:19.000Z","volume":300000,"label":" ","price":0.037},{"type":"A","date":"2018-04-18T05:00:54.000Z","volume":100000,"label":" ","price":0.037},{"type":"B","date":"2018-04-18T05:28:49.000Z","volume":100000,"label":" ","price":0.037},{"type":"U","date":"2018-04-18T05:28:49.000Z","volume":360000,"label":" ","price":0.037},{"type":"A","date":"2018-04-18T05:43:45.000Z","volume":140000,"label":" ","price":0.039},{"type":"B","date":"2018-04-18T06:10:02.000Z","volume":450000,"label":" ","price":0.037},{"type":"A","date":"2018-04-18T06:17:21.000Z","volume":300000,"label":" ","price":0.037},{"type":"B","date":"2018-04-18T06:22:30.000Z","volume":200000,"label":" ","price":0.035},{"type":"A","date":"2018-04-18T07:17:07.000Z","volume":30000,"label":" ","price":0.037},{"type":"A","date":"2018-04-18T07:24:29.000Z","volume":10000,"label":" ","price":0.037}]