[{"type":"B","date":"2018-04-23T02:37:34.000Z","volume":2000,"label":" ","price":1.6},{"type":"A","date":"2018-04-23T02:37:35.000Z","volume":6000,"label":" ","price":1.59},{"type":"B","date":"2018-04-23T03:04:29.000Z","volume":2000,"label":" ","price":1.59},{"type":"A","date":"2018-04-23T03:19:37.000Z","volume":2000,"label":" ","price":1.63},{"type":"A","date":"2018-04-23T05:00:03.000Z","volume":2000,"label":" ","price":1.61},{"type":"A","date":"2018-04-23T06:58:42.000Z","volume":2000,"label":" ","price":1.6},{"type":"B","date":"2018-04-23T07:48:28.000Z","volume":46000,"label":" ","price":1.59},{"type":"B","date":"2018-04-23T07:51:42.000Z","volume":16000,"label":" ","price":1.59}]