{"2017-04-02T16:00:00.000Z":{"date":"2017-04-02T16:00:00.000Z","close":0.51,"change":0,"change_percent":0,"volume":14444472,"volume_price":7196150,"open":0.51,"highest":0.52,"lowest":0.485,"amp":6.86},"2017-04-04T16:00:00.000Z":{"date":"2017-04-04T16:00:00.000Z","close":0.53,"change":0.02,"change_percent":3.9215,"volume":11981236,"volume_price":6111622,"open":0.51,"highest":0.53,"lowest":0.5,"amp":5.88},"2017-04-05T16:00:00.000Z":{"date":"2017-04-05T16:00:00.000Z","close":0.57,"change":0.0399,"change_percent":7.5471,"volume":36610000,"volume_price":20506720,"open":0.53,"highest":0.58,"lowest":0.52,"amp":11.32},"2017-04-06T16:00:00.000Z":{"date":"2017-04-06T16:00:00.000Z","close":0.58,"change":0.01,"change_percent":1.7543,"volume":12530996,"volume_price":7035327,"open":0.59,"highest":0.59,"lowest":0.54,"amp":8.77},"2017-04-09T16:00:00.000Z":{"date":"2017-04-09T16:00:00.000Z","close":0.57,"change":-0.01,"change_percent":-1.7241,"volume":7490000,"volume_price":4221080,"open":0.58,"highest":0.58,"lowest":0.55,"amp":5.17},"2017-04-10T16:00:00.000Z":{"date":"2017-04-10T16:00:00.000Z","close":0.56,"change":-0.0099,"change_percent":-1.7543,"volume":8110180,"volume_price":4530160,"open":0.57,"highest":0.57,"lowest":0.55,"amp":3.5},"2017-04-11T16:00:00.000Z":{"date":"2017-04-11T16:00:00.000Z","close":0.6,"change":0.0399,"change_percent":7.1428,"volume":31555013,"volume_price":18439407,"open":0.56,"highest":0.61,"lowest":0.55,"amp":10.71},"2017-04-12T16:00:00.000Z":{"date":"2017-04-12T16:00:00.000Z","close":0.58,"change":-0.02,"change_percent":-3.3333,"volume":16236000,"volume_price":9454060,"open":0.59,"highest":0.6,"lowest":0.57,"amp":5},"2017-04-17T16:00:00.000Z":{"date":"2017-04-17T16:00:00.000Z","close":0.55,"change":-0.0299,"change_percent":-5.1724,"volume":12872000,"volume_price":7166320,"open":0.57,"highest":0.58,"lowest":0.54,"amp":6.89},"2017-04-18T16:00:00.000Z":{"date":"2017-04-18T16:00:00.000Z","close":0.52,"change":-0.03,"change_percent":-5.4545,"volume":36245145,"volume_price":18527729,"open":0.55,"highest":0.55,"lowest":0.495,"amp":10},"2017-04-19T16:00:00.000Z":{"date":"2017-04-19T16:00:00.000Z","close":0.51,"change":-0.01,"change_percent":-1.923,"volume":9606000,"volume_price":4848000,"open":0.52,"highest":0.52,"lowest":0.5,"amp":3.84},"2017-04-20T16:00:00.000Z":{"date":"2017-04-20T16:00:00.000Z","close":0.52,"change":0.01,"change_percent":1.9607,"volume":7672000,"volume_price":3900640,"open":0.52,"highest":0.52,"lowest":0.5,"amp":3.92},"2017-04-23T16:00:00.000Z":{"date":"2017-04-23T16:00:00.000Z","close":0.51,"change":-0.01,"change_percent":-1.923,"volume":6292000,"volume_price":3184760,"open":0.52,"highest":0.52,"lowest":0.5,"amp":3.84},"2017-04-24T16:00:00.000Z":{"date":"2017-04-24T16:00:00.000Z","close":0.5,"change":-0.01,"change_percent":-1.9607,"volume":9920000,"volume_price":5028120,"open":0.51,"highest":0.52,"lowest":0.5,"amp":3.92},"2017-04-25T16:00:00.000Z":{"date":"2017-04-25T16:00:00.000Z","close":0.5,"change":0,"change_percent":0,"volume":8990000,"volume_price":4494150,"open":0.5,"highest":0.51,"lowest":0.49,"amp":4},"2017-04-26T16:00:00.000Z":{"date":"2017-04-26T16:00:00.000Z","close":0.495,"change":-0.005,"change_percent":-1,"volume":7494000,"volume_price":3698540,"open":0.5,"highest":0.51,"lowest":0.49,"amp":4},"2017-04-27T16:00:00.000Z":{"date":"2017-04-27T16:00:00.000Z","close":0.48,"change":-0.015,"change_percent":-3.0303,"volume":16616000,"volume_price":7897860,"open":0.495,"highest":0.5,"lowest":0.46,"amp":8.08},"2017-05-01T16:00:00.000Z":{"date":"2017-05-01T16:00:00.000Z","close":0.49,"change":0.01,"change_percent":2.0833,"volume":3976000,"volume_price":1920100,"open":0.485,"highest":0.495,"lowest":0.47,"amp":5.2},"2017-05-03T16:00:00.000Z":{"date":"2017-05-03T16:00:00.000Z","close":0.52,"change":0.03,"change_percent":6.1224,"volume":8772000,"volume_price":4429470,"open":0.49,"highest":0.52,"lowest":0.49,"amp":6.12},"2017-05-04T16:00:00.000Z":{"date":"2017-05-04T16:00:00.000Z","close":0.51,"change":-0.01,"change_percent":-1.923,"volume":3930000,"volume_price":1988600,"open":0.52,"highest":0.52,"lowest":0.5,"amp":3.84},"2017-05-07T16:00:00.000Z":{"date":"2017-05-07T16:00:00.000Z","close":0.5,"change":-0.01,"change_percent":-1.9607,"volume":3734000,"volume_price":1865780,"open":0.5,"highest":0.51,"lowest":0.495,"amp":2.94},"2017-05-08T16:00:00.000Z":{"date":"2017-05-08T16:00:00.000Z","close":0.495,"change":-0.005,"change_percent":-1,"volume":2692000,"volume_price":1341600,"open":0.51,"highest":0.51,"lowest":0.49,"amp":4},"2017-05-09T16:00:00.000Z":{"date":"2017-05-09T16:00:00.000Z","close":0.48,"change":-0.015,"change_percent":-3.0303,"volume":4100000,"volume_price":2018430,"open":0.5,"highest":0.51,"lowest":0.48,"amp":6.06},"2017-05-10T16:00:00.000Z":{"date":"2017-05-10T16:00:00.000Z","close":0.48,"change":0,"change_percent":0,"volume":4224000,"volume_price":2038400,"open":0.485,"highest":0.495,"lowest":0.475,"amp":4.16},"2017-05-11T16:00:00.000Z":{"date":"2017-05-11T16:00:00.000Z","close":0.48,"change":0,"change_percent":0,"volume":3226000,"volume_price":1550800,"open":0.485,"highest":0.49,"lowest":0.475,"amp":3.12},"2017-05-14T16:00:00.000Z":{"date":"2017-05-14T16:00:00.000Z","close":0.455,"change":-0.025,"change_percent":-5.2083,"volume":18668000,"volume_price":8568170,"open":0.485,"highest":0.485,"lowest":0.45,"amp":7.29},"2017-05-15T16:00:00.000Z":{"date":"2017-05-15T16:00:00.000Z","close":0.455,"change":0,"change_percent":0,"volume":9098000,"volume_price":4135650,"open":0.47,"highest":0.47,"lowest":0.445,"amp":5.49},"2017-05-16T16:00:00.000Z":{"date":"2017-05-16T16:00:00.000Z","close":0.46,"change":0.005,"change_percent":1.0989,"volume":5964000,"volume_price":2714730,"open":0.455,"highest":0.465,"lowest":0.445,"amp":4.39},"2017-05-17T16:00:00.000Z":{"date":"2017-05-17T16:00:00.000Z","close":0.455,"change":-0.005,"change_percent":-1.0869,"volume":3420000,"volume_price":1533870,"open":0.45,"highest":0.46,"lowest":0.445,"amp":3.26},"2017-05-18T16:00:00.000Z":{"date":"2017-05-18T16:00:00.000Z","close":0.465,"change":0.01,"change_percent":2.1978,"volume":16454000,"volume_price":7414090,"open":0.455,"highest":0.465,"lowest":0.445,"amp":4.39},"2017-05-21T16:00:00.000Z":{"date":"2017-05-21T16:00:00.000Z","close":0.465,"change":0,"change_percent":0,"volume":9206000,"volume_price":4242080,"open":0.465,"highest":0.47,"lowest":0.45,"amp":4.3},"2017-05-22T16:00:00.000Z":{"date":"2017-05-22T16:00:00.000Z","close":0.46,"change":-0.005,"change_percent":-1.0752,"volume":9894000,"volume_price":4578630,"open":0.46,"highest":0.475,"lowest":0.455,"amp":4.3},"2017-05-23T16:00:00.000Z":{"date":"2017-05-23T16:00:00.000Z","close":0.45,"change":-0.01,"change_percent":-2.1739,"volume":4848000,"volume_price":2225270,"open":0.455,"highest":0.47,"lowest":0.45,"amp":4.34},"2017-05-24T16:00:00.000Z":{"date":"2017-05-24T16:00:00.000Z","close":0.46,"change":0.01,"change_percent":2.2222,"volume":4864000,"volume_price":2229590,"open":0.45,"highest":0.465,"lowest":0.45,"amp":3.33},"2017-05-25T16:00:00.000Z":{"date":"2017-05-25T16:00:00.000Z","close":0.455,"change":-0.005,"change_percent":-1.0869,"volume":3812000,"volume_price":1731360,"open":0.455,"highest":0.465,"lowest":0.45,"amp":3.26},"2017-05-28T16:00:00.000Z":{"date":"2017-05-28T16:00:00.000Z","close":0.45,"change":-0.005,"change_percent":-1.0989,"volume":2450000,"volume_price":1102360,"open":0.455,"highest":0.455,"lowest":0.445,"amp":2.19},"2017-05-30T16:00:00.000Z":{"date":"2017-05-30T16:00:00.000Z","close":0.46,"change":0.01,"change_percent":2.2222,"volume":3820000,"volume_price":1741210,"open":0.45,"highest":0.46,"lowest":0.445,"amp":3.33},"2017-05-31T16:00:00.000Z":{"date":"2017-05-31T16:00:00.000Z","close":0.45,"change":-0.01,"change_percent":-2.1739,"volume":2144000,"volume_price":970710,"open":0.45,"highest":0.46,"lowest":0.45,"amp":2.17},"2017-06-01T16:00:00.000Z":{"date":"2017-06-01T16:00:00.000Z","close":0.455,"change":0.005,"change_percent":1.1111,"volume":5526000,"volume_price":2486250,"open":0.45,"highest":0.46,"lowest":0.44,"amp":4.44},"2017-06-04T16:00:00.000Z":{"date":"2017-06-04T16:00:00.000Z","close":0.445,"change":-0.01,"change_percent":-2.1978,"volume":5794000,"volume_price":2605280,"open":0.45,"highest":0.46,"lowest":0.44,"amp":4.39},"2017-06-05T16:00:00.000Z":{"date":"2017-06-05T16:00:00.000Z","close":0.45,"change":0.005,"change_percent":1.1235,"volume":5340000,"volume_price":2385740,"open":0.45,"highest":0.455,"lowest":0.44,"amp":3.37},"2017-06-06T16:00:00.000Z":{"date":"2017-06-06T16:00:00.000Z","close":0.45,"change":0,"change_percent":0,"volume":2510000,"volume_price":1122130,"open":0.45,"highest":0.455,"lowest":0.445,"amp":2.22},"2017-06-07T16:00:00.000Z":{"date":"2017-06-07T16:00:00.000Z","close":0.52,"change":0.07,"change_percent":15.5555,"volume":43649259,"volume_price":21755979,"open":0.445,"highest":0.52,"lowest":0.44,"amp":17.77},"2017-06-08T16:00:00.000Z":{"date":"2017-06-08T16:00:00.000Z","close":0.51,"change":-0.01,"change_percent":-1.923,"volume":26280000,"volume_price":13373050,"open":0.52,"highest":0.53,"lowest":0.495,"amp":6.73},"2017-06-11T16:00:00.000Z":{"date":"2017-06-11T16:00:00.000Z","close":0.485,"change":-0.025,"change_percent":-4.9019,"volume":9292000,"volume_price":4560120,"open":0.5,"highest":0.51,"lowest":0.475,"amp":6.86},"2017-06-12T16:00:00.000Z":{"date":"2017-06-12T16:00:00.000Z","close":0.49,"change":0.005,"change_percent":1.0309,"volume":12442000,"volume_price":6106020,"open":0.485,"highest":0.5,"lowest":0.48,"amp":4.12},"2017-06-13T16:00:00.000Z":{"date":"2017-06-13T16:00:00.000Z","close":0.48,"change":-0.01,"change_percent":-2.0408,"volume":5304000,"volume_price":2564310,"open":0.485,"highest":0.495,"lowest":0.48,"amp":3.06},"2017-06-14T16:00:00.000Z":{"date":"2017-06-14T16:00:00.000Z","close":0.47,"change":-0.01,"change_percent":-2.0833,"volume":5184000,"volume_price":2431520,"open":0.48,"highest":0.48,"lowest":0.46,"amp":4.16},"2017-06-15T16:00:00.000Z":{"date":"2017-06-15T16:00:00.000Z","close":0.44,"change":-0.03,"change_percent":-6.3829,"volume":18245184,"volume_price":8213283,"open":0.465,"highest":0.47,"lowest":0.44,"amp":6.38},"2017-06-18T16:00:00.000Z":{"date":"2017-06-18T16:00:00.000Z","close":0.445,"change":0.005,"change_percent":1.1363,"volume":15121995,"volume_price":6761127,"open":0.45,"highest":0.455,"lowest":0.44,"amp":3.4},"2017-06-19T16:00:00.000Z":{"date":"2017-06-19T16:00:00.000Z","close":0.44,"change":-0.005,"change_percent":-1.1235,"volume":5781949,"volume_price":2563128,"open":0.44,"highest":0.45,"lowest":0.44,"amp":2.24},"2017-06-20T16:00:00.000Z":{"date":"2017-06-20T16:00:00.000Z","close":0.44,"change":0,"change_percent":0,"volume":6362000,"volume_price":2774610,"open":0.44,"highest":0.445,"lowest":0.425,"amp":4.54},"2017-06-21T16:00:00.000Z":{"date":"2017-06-21T16:00:00.000Z","close":0.45,"change":0.01,"change_percent":2.2727,"volume":3600000,"volume_price":1611640,"open":0.45,"highest":0.455,"lowest":0.44,"amp":3.4},"2017-06-22T16:00:00.000Z":{"date":"2017-06-22T16:00:00.000Z","close":0.44,"change":-0.01,"change_percent":-2.2222,"volume":2422000,"volume_price":1086630,"open":0.46,"highest":0.46,"lowest":0.44,"amp":4.44},"2017-06-25T16:00:00.000Z":{"date":"2017-06-25T16:00:00.000Z","close":0.445,"change":0.005,"change_percent":1.1363,"volume":4950000,"volume_price":2226890,"open":0.445,"highest":0.455,"lowest":0.44,"amp":3.4},"2017-06-26T16:00:00.000Z":{"date":"2017-06-26T16:00:00.000Z","close":0.455,"change":0.01,"change_percent":2.2471,"volume":14435800,"volume_price":6625615,"open":0.445,"highest":0.47,"lowest":0.445,"amp":5.61},"2017-06-27T16:00:00.000Z":{"date":"2017-06-27T16:00:00.000Z","close":0.435,"change":-0.02,"change_percent":-4.3956,"volume":9166000,"volume_price":4055460,"open":0.455,"highest":0.455,"lowest":0.435,"amp":4.39},"2017-06-28T16:00:00.000Z":{"date":"2017-06-28T16:00:00.000Z","close":0.45,"change":0.015,"change_percent":3.4482,"volume":4434000,"volume_price":1965540,"open":0.44,"highest":0.45,"lowest":0.435,"amp":3.44},"2017-06-29T16:00:00.000Z":{"date":"2017-06-29T16:00:00.000Z","close":0.44,"change":-0.01,"change_percent":-2.2222,"volume":1540000,"volume_price":681700,"open":0.45,"highest":0.45,"lowest":0.435,"amp":3.33}}