{"2016-03-31T16:00:00.000Z":{"date":"2016-03-31T16:00:00.000Z","close":3.89,"change":0.03,"change_percent":0.7772,"volume":22000,"volume_price":85520,"open":3.86,"highest":3.9,"lowest":3.86,"amp":1.03},"2016-04-04T16:00:00.000Z":{"date":"2016-04-04T16:00:00.000Z","close":3.78,"change":-0.11,"change_percent":-2.8277,"volume":3720,"volume_price":13980,"open":3.78,"highest":3.78,"lowest":3.78,"amp":0},"2016-04-05T16:00:00.000Z":{"date":"2016-04-05T16:00:00.000Z","close":3.77,"change":-0.0099,"change_percent":-0.2645,"volume":2000,"volume_price":7540,"open":3.77,"highest":3.77,"lowest":3.77,"amp":0},"2016-04-06T16:00:00.000Z":{"date":"2016-04-06T16:00:00.000Z","close":3.68,"change":-0.0899,"change_percent":-2.3872,"volume":180514,"volume_price":670731,"open":3.77,"highest":3.77,"lowest":3.66,"amp":2.91},"2016-04-07T16:00:00.000Z":{"date":"2016-04-07T16:00:00.000Z","close":3.61,"change":-0.07,"change_percent":-1.9021,"volume":44000,"volume_price":159660,"open":3.7,"highest":3.7,"lowest":3.6,"amp":2.71},"2016-04-10T16:00:00.000Z":{"date":"2016-04-10T16:00:00.000Z","close":3.62,"change":0.01,"change_percent":0.277,"volume":42964,"volume_price":157269,"open":3.65,"highest":3.68,"lowest":3.61,"amp":1.93},"2016-04-11T16:00:00.000Z":{"date":"2016-04-11T16:00:00.000Z","close":3.61,"change":-0.01,"change_percent":-0.2762,"volume":27000,"volume_price":97680,"open":3.65,"highest":3.65,"lowest":3.61,"amp":1.1},"2016-04-12T16:00:00.000Z":{"date":"2016-04-12T16:00:00.000Z","close":3.69,"change":0.08,"change_percent":2.216,"volume":4000,"volume_price":14760,"open":3.69,"highest":3.69,"lowest":3.69,"amp":0},"2016-04-13T16:00:00.000Z":{"date":"2016-04-13T16:00:00.000Z","close":3.7,"change":0.01,"change_percent":0.271,"volume":28000,"volume_price":103660,"open":3.71,"highest":3.71,"lowest":3.7,"amp":0.27},"2016-04-14T16:00:00.000Z":{"date":"2016-04-14T16:00:00.000Z","close":3.68,"change":-0.02,"change_percent":-0.5405,"volume":7551,"volume_price":27494,"open":3.66,"highest":3.66,"lowest":3.66,"amp":0},"2016-04-17T16:00:00.000Z":{"date":"2016-04-17T16:00:00.000Z","close":3.68,"change":0,"change_percent":0,"volume":8000,"volume_price":29440,"open":3.68,"highest":3.68,"lowest":3.68,"amp":0},"2016-04-18T16:00:00.000Z":{"date":"2016-04-18T16:00:00.000Z","close":3.68,"change":0,"change_percent":0,"volume":0,"volume_price":0,"open":3.68,"highest":3.68,"lowest":3.68,"amp":0},"2016-04-19T16:00:00.000Z":{"date":"2016-04-19T16:00:00.000Z","close":3.68,"change":0,"change_percent":0,"volume":12000,"volume_price":44160,"open":3.68,"highest":3.68,"lowest":3.68,"amp":0},"2016-04-20T16:00:00.000Z":{"date":"2016-04-20T16:00:00.000Z","close":3.68,"change":0,"change_percent":0,"volume":2000,"volume_price":7360,"open":3.68,"highest":3.68,"lowest":3.68,"amp":0},"2016-04-21T16:00:00.000Z":{"date":"2016-04-21T16:00:00.000Z","close":3.7,"change":0.02,"change_percent":0.5434,"volume":166000,"volume_price":612040,"open":3.66,"highest":3.71,"lowest":3.66,"amp":1.35},"2016-04-24T16:00:00.000Z":{"date":"2016-04-24T16:00:00.000Z","close":3.72,"change":0.02,"change_percent":0.5405,"volume":29000,"volume_price":107520,"open":3.7,"highest":3.72,"lowest":3.69,"amp":0.81},"2016-04-25T16:00:00.000Z":{"date":"2016-04-25T16:00:00.000Z","close":3.75,"change":0.0299,"change_percent":0.8064,"volume":226000,"volume_price":837960,"open":3.65,"highest":3.75,"lowest":3.62,"amp":3.49},"2016-04-26T16:00:00.000Z":{"date":"2016-04-26T16:00:00.000Z","close":3.75,"change":0,"change_percent":0,"volume":174000,"volume_price":647680,"open":3.7,"highest":3.75,"lowest":3.65,"amp":2.66},"2016-04-27T16:00:00.000Z":{"date":"2016-04-27T16:00:00.000Z","close":3.71,"change":-0.04,"change_percent":-1.0666,"volume":30000,"volume_price":111500,"open":3.75,"highest":3.75,"lowest":3.7,"amp":1.33},"2016-04-28T16:00:00.000Z":{"date":"2016-04-28T16:00:00.000Z","close":3.74,"change":0.03,"change_percent":0.8086,"volume":94431,"volume_price":352097,"open":3.73,"highest":3.74,"lowest":3.7,"amp":1.07},"2016-05-02T16:00:00.000Z":{"date":"2016-05-02T16:00:00.000Z","close":3.68,"change":-0.06,"change_percent":-1.6042,"volume":48000,"volume_price":179300,"open":3.74,"highest":3.75,"lowest":3.68,"amp":1.87},"2016-05-03T16:00:00.000Z":{"date":"2016-05-03T16:00:00.000Z","close":3.68,"change":0,"change_percent":0,"volume":110000,"volume_price":404640,"open":3.68,"highest":3.69,"lowest":3.66,"amp":0.81},"2016-05-04T16:00:00.000Z":{"date":"2016-05-04T16:00:00.000Z","close":3.71,"change":0.0299,"change_percent":0.8152,"volume":69000,"volume_price":256000,"open":3.73,"highest":3.73,"lowest":3.7,"amp":0.81},"2016-05-05T16:00:00.000Z":{"date":"2016-05-05T16:00:00.000Z","close":3.69,"change":-0.02,"change_percent":-0.539,"volume":0,"volume_price":0,"open":3.69,"highest":3.69,"lowest":3.69,"amp":0},"2016-05-08T16:00:00.000Z":{"date":"2016-05-08T16:00:00.000Z","close":3.65,"change":-0.04,"change_percent":-1.084,"volume":72000,"volume_price":264280,"open":3.68,"highest":3.68,"lowest":3.65,"amp":0.81},"2016-05-09T16:00:00.000Z":{"date":"2016-05-09T16:00:00.000Z","close":3.65,"change":0,"change_percent":0,"volume":0,"volume_price":0,"open":3.65,"highest":3.65,"lowest":3.65,"amp":0},"2016-05-10T16:00:00.000Z":{"date":"2016-05-10T16:00:00.000Z","close":3.61,"change":-0.04,"change_percent":-1.0958,"volume":46504,"volume_price":168554,"open":3.65,"highest":3.65,"lowest":3.6,"amp":1.36},"2016-05-11T16:00:00.000Z":{"date":"2016-05-11T16:00:00.000Z","close":3.61,"change":0,"change_percent":0,"volume":0,"volume_price":0,"open":3.61,"highest":3.61,"lowest":3.6,"amp":0},"2016-05-12T16:00:00.000Z":{"date":"2016-05-12T16:00:00.000Z","close":3.53,"change":-0.08,"change_percent":-2.216,"volume":10000,"volume_price":35460,"open":3.56,"highest":3.61,"lowest":3.52,"amp":2.21},"2016-05-15T16:00:00.000Z":{"date":"2016-05-15T16:00:00.000Z","close":3.45,"change":-0.0799,"change_percent":-2.2662,"volume":98000,"volume_price":340300,"open":3.49,"highest":3.57,"lowest":3.4,"amp":3.39},"2016-05-16T16:00:00.000Z":{"date":"2016-05-16T16:00:00.000Z","close":3.4,"change":-0.05,"change_percent":-1.4492,"volume":36000,"volume_price":124180,"open":3.5,"highest":3.51,"lowest":3.4,"amp":3.18},"2016-05-17T16:00:00.000Z":{"date":"2016-05-17T16:00:00.000Z","close":3.38,"change":-0.02,"change_percent":-0.5882,"volume":30205,"volume_price":102624,"open":3.4,"highest":3.49,"lowest":3.38,"amp":3.23},"2016-05-18T16:00:00.000Z":{"date":"2016-05-18T16:00:00.000Z","close":3.38,"change":0,"change_percent":0,"volume":18000,"volume_price":60020,"open":3.3,"highest":3.38,"lowest":3.3,"amp":0},"2016-05-19T16:00:00.000Z":{"date":"2016-05-19T16:00:00.000Z","close":3.4,"change":0.02,"change_percent":0.5917,"volume":20000,"volume_price":67780,"open":3.38,"highest":3.4,"lowest":3.38,"amp":0},"2016-05-22T16:00:00.000Z":{"date":"2016-05-22T16:00:00.000Z","close":3.42,"change":0.02,"change_percent":0.5882,"volume":54000,"volume_price":184240,"open":3.4,"highest":3.42,"lowest":3.38,"amp":0},"2016-05-23T16:00:00.000Z":{"date":"2016-05-23T16:00:00.000Z","close":3.41,"change":-0.0099,"change_percent":-0.2923,"volume":0,"volume_price":0,"open":3.41,"highest":3.42,"lowest":3.41,"amp":0.29},"2016-05-24T16:00:00.000Z":{"date":"2016-05-24T16:00:00.000Z","close":3.41,"change":0,"change_percent":0,"volume":0,"volume_price":0,"open":3.41,"highest":3.41,"lowest":3.41,"amp":0},"2016-05-25T16:00:00.000Z":{"date":"2016-05-25T16:00:00.000Z","close":3.41,"change":0,"change_percent":0,"volume":1000,"volume_price":3330,"open":3.41,"highest":3.41,"lowest":3.41,"amp":0},"2016-05-26T16:00:00.000Z":{"date":"2016-05-26T16:00:00.000Z","close":3.41,"change":0,"change_percent":0,"volume":571,"volume_price":1901,"open":3.41,"highest":3.41,"lowest":3.41,"amp":0},"2016-05-29T16:00:00.000Z":{"date":"2016-05-29T16:00:00.000Z","close":3.38,"change":-0.03,"change_percent":-0.8797,"volume":5599,"volume_price":18850,"open":3.38,"highest":3.41,"lowest":3.38,"amp":0.87},"2016-05-30T16:00:00.000Z":{"date":"2016-05-30T16:00:00.000Z","close":3.4,"change":0.02,"change_percent":0.5917,"volume":0,"volume_price":0,"open":3.4,"highest":3.4,"lowest":3.38,"amp":0},"2016-05-31T16:00:00.000Z":{"date":"2016-05-31T16:00:00.000Z","close":3.4,"change":0,"change_percent":0,"volume":14000,"volume_price":47600,"open":3.39,"highest":3.41,"lowest":3.39,"amp":0.29},"2016-06-01T16:00:00.000Z":{"date":"2016-06-01T16:00:00.000Z","close":3.4,"change":0,"change_percent":0,"volume":0,"volume_price":0,"open":3.4,"highest":3.4,"lowest":3.4,"amp":0},"2016-06-02T16:00:00.000Z":{"date":"2016-06-02T16:00:00.000Z","close":3.4,"change":0,"change_percent":0,"volume":24000,"volume_price":81440,"open":3.38,"highest":3.4,"lowest":3.38,"amp":0},"2016-06-05T16:00:00.000Z":{"date":"2016-06-05T16:00:00.000Z","close":3.33,"change":-0.0699,"change_percent":-2.0588,"volume":58000,"volume_price":191740,"open":3.31,"highest":3.33,"lowest":3.23,"amp":2.05},"2016-06-06T16:00:00.000Z":{"date":"2016-06-06T16:00:00.000Z","close":3.36,"change":0.0299,"change_percent":0.9009,"volume":48000,"volume_price":161700,"open":3.34,"highest":3.41,"lowest":3.25,"amp":1.5},"2016-06-07T16:00:00.000Z":{"date":"2016-06-07T16:00:00.000Z","close":3.31,"change":-0.0499,"change_percent":-1.488,"volume":18125,"volume_price":60308,"open":3.35,"highest":3.36,"lowest":3.31,"amp":1.48},"2016-06-09T16:00:00.000Z":{"date":"2016-06-09T16:00:00.000Z","close":3.41,"change":0.1,"change_percent":3.0211,"volume":102000,"volume_price":337320,"open":3.26,"highest":3.41,"lowest":3.26,"amp":0},"2016-06-12T16:00:00.000Z":{"date":"2016-06-12T16:00:00.000Z","close":3.41,"change":0,"change_percent":0,"volume":98000,"volume_price":329360,"open":3.32,"highest":3.41,"lowest":3.32,"amp":0},"2016-06-13T16:00:00.000Z":{"date":"2016-06-13T16:00:00.000Z","close":3.46,"change":0.0499,"change_percent":1.4662,"volume":49000,"volume_price":168350,"open":3.35,"highest":3.46,"lowest":3.35,"amp":0},"2016-06-14T16:00:00.000Z":{"date":"2016-06-14T16:00:00.000Z","close":3.52,"change":0.06,"change_percent":1.7341,"volume":234400,"volume_price":807820,"open":3.4,"highest":3.52,"lowest":3.4,"amp":0},"2016-06-15T16:00:00.000Z":{"date":"2016-06-15T16:00:00.000Z","close":3.59,"change":0.0699,"change_percent":1.9886,"volume":216050,"volume_price":752570,"open":3.46,"highest":3.59,"lowest":3.44,"amp":0},"2016-06-16T16:00:00.000Z":{"date":"2016-06-16T16:00:00.000Z","close":3.56,"change":-0.0299,"change_percent":-0.8356,"volume":532000,"volume_price":1893860,"open":3.51,"highest":3.67,"lowest":3.5,"amp":3.06},"2016-06-19T16:00:00.000Z":{"date":"2016-06-19T16:00:00.000Z","close":3.63,"change":0.0699,"change_percent":1.9662,"volume":56000,"volume_price":201700,"open":3.59,"highest":3.63,"lowest":3.51,"amp":0},"2016-06-20T16:00:00.000Z":{"date":"2016-06-20T16:00:00.000Z","close":3.66,"change":0.03,"change_percent":0.8264,"volume":128000,"volume_price":463700,"open":3.58,"highest":3.66,"lowest":3.56,"amp":0},"2016-06-21T16:00:00.000Z":{"date":"2016-06-21T16:00:00.000Z","close":3.68,"change":0.02,"change_percent":0.5464,"volume":74000,"volume_price":271260,"open":3.54,"highest":3.69,"lowest":3.54,"amp":0.27},"2016-06-22T16:00:00.000Z":{"date":"2016-06-22T16:00:00.000Z","close":3.68,"change":0,"change_percent":0,"volume":33000,"volume_price":120850,"open":3.66,"highest":3.68,"lowest":3.66,"amp":0},"2016-06-23T16:00:00.000Z":{"date":"2016-06-23T16:00:00.000Z","close":3.68,"change":0,"change_percent":0,"volume":64000,"volume_price":230500,"open":3.3,"highest":3.68,"lowest":3.3,"amp":0},"2016-06-26T16:00:00.000Z":{"date":"2016-06-26T16:00:00.000Z","close":3.6,"change":-0.08,"change_percent":-2.1739,"volume":26636,"volume_price":95837,"open":3.6,"highest":3.68,"lowest":3.59,"amp":2.17},"2016-06-27T16:00:00.000Z":{"date":"2016-06-27T16:00:00.000Z","close":3.68,"change":0.08,"change_percent":2.2222,"volume":139200,"volume_price":505128,"open":3.65,"highest":3.68,"lowest":3.54,"amp":0},"2016-06-28T16:00:00.000Z":{"date":"2016-06-28T16:00:00.000Z","close":3.74,"change":0.06,"change_percent":1.6304,"volume":190000,"volume_price":701900,"open":3.68,"highest":3.74,"lowest":3.62,"amp":0},"2016-06-29T16:00:00.000Z":{"date":"2016-06-29T16:00:00.000Z","close":3.82,"change":0.0799,"change_percent":2.139,"volume":366000,"volume_price":1389280,"open":3.8,"highest":3.82,"lowest":3.64,"amp":0}}