{"2016-03-31T16:00:00.000Z":{"date":"2016-03-31T16:00:00.000Z","close":3.62,"change":-0.1,"change_percent":-2.6881,"volume":2150000,"volume_price":7827150,"open":3.7,"highest":3.7,"lowest":3.6,"amp":2.68},"2016-04-04T16:00:00.000Z":{"date":"2016-04-04T16:00:00.000Z","close":3.52,"change":-0.1,"change_percent":-2.7624,"volume":2594000,"volume_price":9193440,"open":3.64,"highest":3.64,"lowest":3.5,"amp":3.86},"2016-04-05T16:00:00.000Z":{"date":"2016-04-05T16:00:00.000Z","close":3.6,"change":0.08,"change_percent":2.2727,"volume":2210028,"volume_price":7900181,"open":3.5,"highest":3.63,"lowest":3.5,"amp":3.69},"2016-04-06T16:00:00.000Z":{"date":"2016-04-06T16:00:00.000Z","close":3.6,"change":0,"change_percent":0,"volume":1664000,"volume_price":5985840,"open":3.61,"highest":3.64,"lowest":3.58,"amp":1.66},"2016-04-07T16:00:00.000Z":{"date":"2016-04-07T16:00:00.000Z","close":3.58,"change":-0.02,"change_percent":-0.5555,"volume":1558000,"volume_price":5546590,"open":3.58,"highest":3.58,"lowest":3.54,"amp":1.11},"2016-04-10T16:00:00.000Z":{"date":"2016-04-10T16:00:00.000Z","close":3.65,"change":0.0699,"change_percent":1.9553,"volume":1968000,"volume_price":7143860,"open":3.59,"highest":3.71,"lowest":3.57,"amp":3.91},"2016-04-11T16:00:00.000Z":{"date":"2016-04-11T16:00:00.000Z","close":3.73,"change":0.08,"change_percent":2.1917,"volume":2608000,"volume_price":9603436,"open":3.65,"highest":3.74,"lowest":3.62,"amp":3.28},"2016-04-12T16:00:00.000Z":{"date":"2016-04-12T16:00:00.000Z","close":3.97,"change":0.24,"change_percent":6.4343,"volume":6548000,"volume_price":25649192,"open":3.8,"highest":4.01,"lowest":3.76,"amp":6.7},"2016-04-13T16:00:00.000Z":{"date":"2016-04-13T16:00:00.000Z","close":4.05,"change":0.0799,"change_percent":2.0151,"volume":8970000,"volume_price":35970920,"open":3.99,"highest":4.11,"lowest":3.88,"amp":5.79},"2016-04-14T16:00:00.000Z":{"date":"2016-04-14T16:00:00.000Z","close":4.05,"change":0,"change_percent":0,"volume":6230000,"volume_price":25226010,"open":4.08,"highest":4.11,"lowest":4,"amp":2.71},"2016-04-17T16:00:00.000Z":{"date":"2016-04-17T16:00:00.000Z","close":4,"change":-0.0499,"change_percent":-1.2345,"volume":3020000,"volume_price":12031520,"open":4.03,"highest":4.03,"lowest":3.95,"amp":1.97},"2016-04-18T16:00:00.000Z":{"date":"2016-04-18T16:00:00.000Z","close":4.04,"change":0.04,"change_percent":1,"volume":5142012,"volume_price":20621827,"open":4.08,"highest":4.08,"lowest":3.98,"amp":2.5},"2016-04-19T16:00:00.000Z":{"date":"2016-04-19T16:00:00.000Z","close":3.95,"change":-0.0899,"change_percent":-2.2277,"volume":2136000,"volume_price":8475050,"open":4.09,"highest":4.09,"lowest":3.91,"amp":4.45},"2016-04-20T16:00:00.000Z":{"date":"2016-04-20T16:00:00.000Z","close":4.059,"change":0.109,"change_percent":2.7594,"volume":1670800,"volume_price":6747770,"open":4.019,"highest":4.08,"lowest":3.97,"amp":2.78},"2016-04-21T16:00:00.000Z":{"date":"2016-04-21T16:00:00.000Z","close":4.07,"change":0.011,"change_percent":0.271,"volume":1812000,"volume_price":7343730,"open":4.059,"highest":4.07,"lowest":4.019,"amp":1.25},"2016-04-24T16:00:00.000Z":{"date":"2016-04-24T16:00:00.000Z","close":4.11,"change":0.04,"change_percent":0.9828,"volume":4580000,"volume_price":18788560,"open":4.059,"highest":4.18,"lowest":4.04,"amp":3.43},"2016-04-25T16:00:00.000Z":{"date":"2016-04-25T16:00:00.000Z","close":4.11,"change":0,"change_percent":0,"volume":4582000,"volume_price":18784580,"open":4.1,"highest":4.14,"lowest":4.08,"amp":1.45},"2016-04-26T16:00:00.000Z":{"date":"2016-04-26T16:00:00.000Z","close":4.11,"change":0,"change_percent":0,"volume":648000,"volume_price":2667990,"open":4.1,"highest":4.15,"lowest":4.09,"amp":1.45},"2016-04-27T16:00:00.000Z":{"date":"2016-04-27T16:00:00.000Z","close":4.14,"change":0.0299,"change_percent":0.7299,"volume":854000,"volume_price":3561120,"open":4.15,"highest":4.2,"lowest":4.1,"amp":2.43},"2016-04-28T16:00:00.000Z":{"date":"2016-04-28T16:00:00.000Z","close":4.1,"change":-0.04,"change_percent":-0.9661,"volume":618000,"volume_price":2528750,"open":4.08,"highest":4.13,"lowest":4.059,"amp":1.71},"2016-05-02T16:00:00.000Z":{"date":"2016-05-02T16:00:00.000Z","close":4.01,"change":-0.0899,"change_percent":-2.1951,"volume":2260000,"volume_price":9182500,"open":4.08,"highest":4.1,"lowest":3.98,"amp":2.92},"2016-05-03T16:00:00.000Z":{"date":"2016-05-03T16:00:00.000Z","close":3.91,"change":-0.0999,"change_percent":-2.4937,"volume":1992000,"volume_price":7995850,"open":3.93,"highest":3.96,"lowest":3.89,"amp":1.74},"2016-05-04T16:00:00.000Z":{"date":"2016-05-04T16:00:00.000Z","close":3.81,"change":-0.1,"change_percent":-2.5575,"volume":1268000,"volume_price":4835100,"open":3.9,"highest":3.92,"lowest":3.77,"amp":3.83},"2016-05-05T16:00:00.000Z":{"date":"2016-05-05T16:00:00.000Z","close":3.7,"change":-0.11,"change_percent":-2.8871,"volume":1280000,"volume_price":4764680,"open":3.79,"highest":3.79,"lowest":3.69,"amp":2.62},"2016-05-08T16:00:00.000Z":{"date":"2016-05-08T16:00:00.000Z","close":3.71,"change":0.0099,"change_percent":0.2702,"volume":1496000,"volume_price":5536178,"open":3.71,"highest":3.72,"lowest":3.64,"amp":2.16},"2016-05-09T16:00:00.000Z":{"date":"2016-05-09T16:00:00.000Z","close":3.71,"change":0,"change_percent":0,"volume":934000,"volume_price":3455090,"open":3.67,"highest":3.71,"lowest":3.67,"amp":1.07},"2016-05-10T16:00:00.000Z":{"date":"2016-05-10T16:00:00.000Z","close":3.7,"change":-0.0099,"change_percent":-0.2695,"volume":1006000,"volume_price":3715750,"open":3.71,"highest":3.73,"lowest":3.66,"amp":1.88},"2016-05-11T16:00:00.000Z":{"date":"2016-05-11T16:00:00.000Z","close":3.71,"change":0.0099,"change_percent":0.2702,"volume":630000,"volume_price":2324450,"open":3.7,"highest":3.73,"lowest":3.66,"amp":4.05},"2016-05-12T16:00:00.000Z":{"date":"2016-05-12T16:00:00.000Z","close":3.63,"change":-0.08,"change_percent":-2.1563,"volume":1832000,"volume_price":6697690,"open":3.71,"highest":3.72,"lowest":3.63,"amp":2.42},"2016-05-15T16:00:00.000Z":{"date":"2016-05-15T16:00:00.000Z","close":3.67,"change":0.04,"change_percent":1.1019,"volume":930000,"volume_price":3386180,"open":3.57,"highest":3.7,"lowest":3.57,"amp":0.82},"2016-05-16T16:00:00.000Z":{"date":"2016-05-16T16:00:00.000Z","close":3.64,"change":-0.0299,"change_percent":-0.8174,"volume":1876000,"volume_price":6827730,"open":3.69,"highest":3.71,"lowest":3.6,"amp":1.9},"2016-05-17T16:00:00.000Z":{"date":"2016-05-17T16:00:00.000Z","close":3.62,"change":-0.02,"change_percent":-0.5494,"volume":606268,"volume_price":2193001,"open":3.59,"highest":3.64,"lowest":3.59,"amp":0.54},"2016-05-18T16:00:00.000Z":{"date":"2016-05-18T16:00:00.000Z","close":3.65,"change":0.0299,"change_percent":0.8287,"volume":1398000,"volume_price":5090790,"open":3.59,"highest":3.68,"lowest":3.58,"amp":0.82},"2016-05-19T16:00:00.000Z":{"date":"2016-05-19T16:00:00.000Z","close":3.61,"change":-0.04,"change_percent":-1.0958,"volume":1674000,"volume_price":6052480,"open":3.61,"highest":3.67,"lowest":3.57,"amp":1.64},"2016-05-22T16:00:00.000Z":{"date":"2016-05-22T16:00:00.000Z","close":3.58,"change":-0.0299,"change_percent":-0.831,"volume":1518000,"volume_price":5450180,"open":3.58,"highest":3.64,"lowest":3.56,"amp":1.66},"2016-05-23T16:00:00.000Z":{"date":"2016-05-23T16:00:00.000Z","close":3.44,"change":-0.14,"change_percent":-3.9106,"volume":3510000,"volume_price":12210800,"open":3.57,"highest":3.57,"lowest":3.44,"amp":3.91},"2016-05-24T16:00:00.000Z":{"date":"2016-05-24T16:00:00.000Z","close":3.55,"change":0.11,"change_percent":3.1976,"volume":5548000,"volume_price":19331440,"open":3.5,"highest":3.55,"lowest":3.45,"amp":0},"2016-05-25T16:00:00.000Z":{"date":"2016-05-25T16:00:00.000Z","close":3.57,"change":0.02,"change_percent":0.5633,"volume":820000,"volume_price":2919398,"open":3.58,"highest":3.58,"lowest":3.53,"amp":0.56},"2016-05-26T16:00:00.000Z":{"date":"2016-05-26T16:00:00.000Z","close":3.72,"change":0.15,"change_percent":4.2016,"volume":4430000,"volume_price":16349270,"open":3.6,"highest":3.75,"lowest":3.57,"amp":0.84},"2016-05-29T16:00:00.000Z":{"date":"2016-05-29T16:00:00.000Z","close":3.81,"change":0.0899,"change_percent":2.4193,"volume":4048000,"volume_price":15383530,"open":3.79,"highest":3.83,"lowest":3.77,"amp":0.53},"2016-05-30T16:00:00.000Z":{"date":"2016-05-30T16:00:00.000Z","close":3.88,"change":0.0699,"change_percent":1.8372,"volume":3486000,"volume_price":13601620,"open":3.84,"highest":3.97,"lowest":3.81,"amp":2.36},"2016-05-31T16:00:00.000Z":{"date":"2016-05-31T16:00:00.000Z","close":3.94,"change":0.06,"change_percent":1.5463,"volume":2924000,"volume_price":11414070,"open":3.88,"highest":3.94,"lowest":3.85,"amp":0},"2016-06-01T16:00:00.000Z":{"date":"2016-06-01T16:00:00.000Z","close":3.93,"change":-0.0099,"change_percent":-0.2538,"volume":2584000,"volume_price":10151640,"open":3.92,"highest":3.97,"lowest":3.91,"amp":1.01},"2016-06-02T16:00:00.000Z":{"date":"2016-06-02T16:00:00.000Z","close":3.9,"change":-0.03,"change_percent":-0.7633,"volume":770000,"volume_price":3010760,"open":3.97,"highest":3.97,"lowest":3.87,"amp":1.78},"2016-06-05T16:00:00.000Z":{"date":"2016-06-05T16:00:00.000Z","close":3.81,"change":-0.0899,"change_percent":-2.3076,"volume":2417997,"volume_price":9200608,"open":3.88,"highest":3.88,"lowest":3.77,"amp":2.3},"2016-06-06T16:00:00.000Z":{"date":"2016-06-06T16:00:00.000Z","close":3.9,"change":0.0899,"change_percent":2.3622,"volume":4596000,"volume_price":17901000,"open":3.83,"highest":3.94,"lowest":3.82,"amp":1.04},"2016-06-07T16:00:00.000Z":{"date":"2016-06-07T16:00:00.000Z","close":3.91,"change":0.01,"change_percent":0.2564,"volume":2674000,"volume_price":10426670,"open":3.91,"highest":3.91,"lowest":3.85,"amp":0.76},"2016-06-09T16:00:00.000Z":{"date":"2016-06-09T16:00:00.000Z","close":3.75,"change":-0.16,"change_percent":-4.092,"volume":1910000,"volume_price":7256130,"open":3.91,"highest":3.91,"lowest":3.75,"amp":4.09},"2016-06-12T16:00:00.000Z":{"date":"2016-06-12T16:00:00.000Z","close":3.77,"change":0.02,"change_percent":0.5333,"volume":2364000,"volume_price":8853270,"open":3.65,"highest":3.81,"lowest":3.65,"amp":1.06},"2016-06-13T16:00:00.000Z":{"date":"2016-06-13T16:00:00.000Z","close":3.76,"change":-0.01,"change_percent":-0.2652,"volume":2508000,"volume_price":9504774,"open":3.75,"highest":3.86,"lowest":3.71,"amp":2.65},"2016-06-14T16:00:00.000Z":{"date":"2016-06-14T16:00:00.000Z","close":3.81,"change":0.05,"change_percent":1.3297,"volume":3086000,"volume_price":11703540,"open":3.74,"highest":3.85,"lowest":3.74,"amp":1.06},"2016-06-15T16:00:00.000Z":{"date":"2016-06-15T16:00:00.000Z","close":3.79,"change":-0.02,"change_percent":-0.5249,"volume":1474000,"volume_price":5577110,"open":3.83,"highest":3.83,"lowest":3.76,"amp":1.04},"2016-06-16T16:00:00.000Z":{"date":"2016-06-16T16:00:00.000Z","close":3.87,"change":0.08,"change_percent":2.1108,"volume":1510000,"volume_price":5833100,"open":3.82,"highest":3.89,"lowest":3.8,"amp":0.52},"2016-06-19T16:00:00.000Z":{"date":"2016-06-19T16:00:00.000Z","close":4.019,"change":0.149,"change_percent":3.8501,"volume":4436000,"volume_price":17643560,"open":3.89,"highest":4.05,"lowest":3.89,"amp":0.8},"2016-06-20T16:00:00.000Z":{"date":"2016-06-20T16:00:00.000Z","close":4,"change":-0.019,"change_percent":-0.4727,"volume":2992000,"volume_price":11928504,"open":4,"highest":4.05,"lowest":3.93,"amp":1.24},"2016-06-21T16:00:00.000Z":{"date":"2016-06-21T16:00:00.000Z","close":3.95,"change":-0.0499,"change_percent":-1.25,"volume":1516000,"volume_price":5991840,"open":3.97,"highest":4.01,"lowest":3.91,"amp":1.49},"2016-06-22T16:00:00.000Z":{"date":"2016-06-22T16:00:00.000Z","close":3.9,"change":-0.05,"change_percent":-1.2658,"volume":1246000,"volume_price":4878700,"open":3.93,"highest":3.98,"lowest":3.88,"amp":2.02},"2016-06-23T16:00:00.000Z":{"date":"2016-06-23T16:00:00.000Z","close":3.86,"change":-0.04,"change_percent":-1.0256,"volume":4400000,"volume_price":16854200,"open":3.9,"highest":3.93,"lowest":3.68,"amp":1.79},"2016-06-26T16:00:00.000Z":{"date":"2016-06-26T16:00:00.000Z","close":3.9,"change":0.04,"change_percent":1.0362,"volume":1484000,"volume_price":5754770,"open":3.82,"highest":3.95,"lowest":3.78,"amp":1.29},"2016-06-27T16:00:00.000Z":{"date":"2016-06-27T16:00:00.000Z","close":3.77,"change":-0.13,"change_percent":-3.3333,"volume":1530000,"volume_price":5771180,"open":3.82,"highest":3.88,"lowest":3.74,"amp":3.33},"2016-06-28T16:00:00.000Z":{"date":"2016-06-28T16:00:00.000Z","close":3.81,"change":0.04,"change_percent":1.061,"volume":2296000,"volume_price":8744700,"open":3.75,"highest":3.83,"lowest":3.75,"amp":0.53},"2016-06-29T16:00:00.000Z":{"date":"2016-06-29T16:00:00.000Z","close":3.97,"change":0.16,"change_percent":4.1994,"volume":3348000,"volume_price":13265280,"open":3.85,"highest":4,"lowest":3.81,"amp":0.78}}